{
  "proyecto": "LEY.DO",
  "version_esquema": "0.1.0",
  "actualizado_en": "2026-07-04",
  "documentos": [
    {
      "tipo_documento": "decreto",
      "numero": "002",
      "anio": "2026",
      "titulo": "Decreto núm. 002-2026",
      "fecha": "6 de Enero 2026 | 11:53",
      "institucion_fuente": "Presidencia de la República Dominicana",
      "url_fuente_oficial": "https://presidencia.gob.do/decretos/2-26",
      "url_pdf_original": "https://presidencia.gob.do//sites/default/files/decree/2026-01/Decreto%202-26.pdf",
      "fecha_consulta": "2026-07-04",
      "ruta_pdf_local": "archivos/decretos/2026/decreto-002-2026.pdf",
      "ruta_markdown": "docs/decretos/2026/decreto-002-2026.md",
      "ruta_json": "datos/decretos/2026/decreto-002-2026.json",
      "sha256_pdf_original": "0e2bc31f441123875a8c9bf50d450f2da4948a4c1ed95da95f0e5ac18366fd18",
      "sha256_markdown": "2d98431dc276cee4ceb8e3c4ed7e0e3d0d97b36fdea8bf6f139d21b2bb28eabb",
      "estado_revision": "pendiente_revision",
      "estado_publicacion": "normalizado",
      "commit_publicacion": "",
      "notas": "Pendiente de revisión humana. Texto extraído automáticamente desde PDF oficial indicado; verificar contra el PDF antes de publicar como aprobado."
    },
    {
      "tipo_documento": "decreto",
      "numero": "003",
      "anio": "2026",
      "titulo": "Decreto núm. 003-2026",
      "fecha": "6 de Enero 2026 | 18:57",
      "institucion_fuente": "Presidencia de la República Dominicana",
      "url_fuente_oficial": "https://presidencia.gob.do/decretos/3-26",
      "url_pdf_original": "https://presidencia.gob.do//sites/default/files/decree/2026-01/Decreto%203-26.pdf",
      "fecha_consulta": "2026-07-04",
      "ruta_pdf_local": "archivos/decretos/2026/decreto-003-2026.pdf",
      "ruta_markdown": "docs/decretos/2026/decreto-003-2026.md",
      "ruta_json": "datos/decretos/2026/decreto-003-2026.json",
      "sha256_pdf_original": "fc6bdde4d62c25739d0fa952aa2b844931dfa05349f55babac01886ca74624d0",
      "sha256_markdown": "19a51db5a8c5d4ecab6399e547aefe55f197e109684ae3969c081443259c424c",
      "estado_revision": "pendiente_revision",
      "estado_publicacion": "normalizado",
      "commit_publicacion": "",
      "notas": "Pendiente de revisión humana. Texto extraído automáticamente desde PDF oficial indicado; verificar contra el PDF antes de publicar como aprobado."
    },
    {
      "tipo_documento": "decreto",
      "numero": "006",
      "anio": "2026",
      "titulo": "Decreto núm. 006-2026",
      "fecha": "8 de Enero 2026 | 15:49",
      "institucion_fuente": "Presidencia de la República Dominicana",
      "url_fuente_oficial": "https://presidencia.gob.do/decretos/6-26",
      "url_pdf_original": "https://presidencia.gob.do//sites/default/files/decree/2026-01/Decreto%206-26.pdf",
      "fecha_consulta": "2026-07-04",
      "ruta_pdf_local": "archivos/decretos/2026/decreto-006-2026.pdf",
      "ruta_markdown": "docs/decretos/2026/decreto-006-2026.md",
      "ruta_json": "datos/decretos/2026/decreto-006-2026.json",
      "sha256_pdf_original": "5b835e49c2e6a3e43dacd9693dfd5bfd9864440a040ac75192e18c98bc665813",
      "sha256_markdown": "0ba317df623956ee2dacb5b8f4c6d0e1e0d41c5214ed8c40ae39d0c5aca6739f",
      "estado_revision": "pendiente_revision",
      "estado_publicacion": "normalizado",
      "commit_publicacion": "",
      "notas": "Pendiente de revisión humana. Texto extraído automáticamente desde PDF oficial indicado; verificar contra el PDF antes de publicar como aprobado."
    },
    {
      "tipo_documento": "decreto",
      "numero": "041",
      "anio": "2026",
      "titulo": "Decreto núm. 041-2026",
      "fecha": "27 de Enero 2026 | 17:51",
      "institucion_fuente": "Presidencia de la República Dominicana",
      "url_fuente_oficial": "https://presidencia.gob.do/decretos/41-26",
      "url_pdf_original": "https://presidencia.gob.do//sites/default/files/decree/2026-01/Decreto%2041-26.pdf",
      "fecha_consulta": "2026-07-04",
      "ruta_pdf_local": "archivos/decretos/2026/decreto-041-2026.pdf",
      "ruta_markdown": "docs/decretos/2026/decreto-041-2026.md",
      "ruta_json": "datos/decretos/2026/decreto-041-2026.json",
      "sha256_pdf_original": "a6ab66a6d51cff6e104a75cd31b662f4522a835fe584e1f6eba6a15eca6d5c5b",
      "sha256_markdown": "c20e461721f48825a8504eec2a5c4807b04b47b01e4c44530816df745dbf928a",
      "estado_revision": "pendiente_revision",
      "estado_publicacion": "normalizado",
      "commit_publicacion": "",
      "notas": "Pendiente de revisión humana. Texto extraído automáticamente desde PDF oficial indicado; verificar contra el PDF antes de publicar como aprobado."
    },
    {
      "tipo_documento": "decreto",
      "numero": "042",
      "anio": "2026",
      "titulo": "Decreto núm. 042-2026",
      "fecha": "27 de Enero 2026 | 17:53",
      "institucion_fuente": "Presidencia de la República Dominicana",
      "url_fuente_oficial": "https://presidencia.gob.do/decretos/42-26",
      "url_pdf_original": "https://presidencia.gob.do//sites/default/files/decree/2026-01/Decreto%2042-26.pdf",
      "fecha_consulta": "2026-07-04",
      "ruta_pdf_local": "archivos/decretos/2026/decreto-042-2026.pdf",
      "ruta_markdown": "docs/decretos/2026/decreto-042-2026.md",
      "ruta_json": "datos/decretos/2026/decreto-042-2026.json",
      "sha256_pdf_original": "76c5ccaf7b7ce6b09165ccbb5f1d2fc9bcb229f359c465fb4181d7de34b4b448",
      "sha256_markdown": "a089744d55c3541297f6522ce6def67b4dc467f027006b0e42aea923c7611244",
      "estado_revision": "pendiente_revision",
      "estado_publicacion": "normalizado",
      "commit_publicacion": "",
      "notas": "Pendiente de revisión humana. Texto extraído automáticamente desde PDF oficial indicado; verificar contra el PDF antes de publicar como aprobado."
    },
    {
      "tipo_documento": "decreto",
      "numero": "043",
      "anio": "2026",
      "titulo": "Decreto núm. 043-2026",
      "fecha": "27 de Enero 2026 | 17:54",
      "institucion_fuente": "Presidencia de la República Dominicana",
      "url_fuente_oficial": "https://presidencia.gob.do/decretos/43-26",
      "url_pdf_original": "https://presidencia.gob.do//sites/default/files/decree/2026-01/Decreto%2043-26.pdf",
      "fecha_consulta": "2026-07-04",
      "ruta_pdf_local": "archivos/decretos/2026/decreto-043-2026.pdf",
      "ruta_markdown": "docs/decretos/2026/decreto-043-2026.md",
      "ruta_json": "datos/decretos/2026/decreto-043-2026.json",
      "sha256_pdf_original": "d5c378c6a253bf3a58158ec43c5fa019ff34627446ace24cf489222ff64463c2",
      "sha256_markdown": "8e259d08b76227661b69e56eb685c7d224bb30bd15441195933705e9c0a7c080",
      "estado_revision": "pendiente_revision",
      "estado_publicacion": "normalizado",
      "commit_publicacion": "",
      "notas": "Pendiente de revisión humana. Texto extraído automáticamente desde PDF oficial indicado; verificar contra el PDF antes de publicar como aprobado."
    },
    {
      "tipo_documento": "decreto",
      "numero": "055",
      "anio": "2026",
      "titulo": "Decreto núm. 055-2026",
      "fecha": "30 de Enero 2026 | 19:53",
      "institucion_fuente": "Presidencia de la República Dominicana",
      "url_fuente_oficial": "https://presidencia.gob.do/decretos/55-26",
      "url_pdf_original": "https://presidencia.gob.do//sites/default/files/decree/2026-01/Decreto%2055-26_0.pdf",
      "fecha_consulta": "2026-07-04",
      "ruta_pdf_local": "archivos/decretos/2026/decreto-055-2026.pdf",
      "ruta_markdown": "docs/decretos/2026/decreto-055-2026.md",
      "ruta_json": "datos/decretos/2026/decreto-055-2026.json",
      "sha256_pdf_original": "71db561d5a7a614b9ad4e6c1d22236d555105a6e784a41bf89e08f503ae2b936",
      "sha256_markdown": "234e06d8fd4ffefe9745a7d790c481c3458a1d1a3118f59eb8903e92280a947c",
      "estado_revision": "pendiente_revision",
      "estado_publicacion": "normalizado",
      "commit_publicacion": "",
      "notas": "Pendiente de revisión humana. Texto extraído automáticamente desde PDF oficial indicado; verificar contra el PDF antes de publicar como aprobado."
    },
    {
      "tipo_documento": "decreto",
      "numero": "058",
      "anio": "2026",
      "titulo": "Decreto núm. 058-2026",
      "fecha": "30 de Enero 2026 | 18:24",
      "institucion_fuente": "Presidencia de la República Dominicana",
      "url_fuente_oficial": "https://presidencia.gob.do/decretos/58-26",
      "url_pdf_original": "https://presidencia.gob.do//sites/default/files/decree/2026-01/Decreto%2058-26.pdf",
      "fecha_consulta": "2026-07-04",
      "ruta_pdf_local": "archivos/decretos/2026/decreto-058-2026.pdf",
      "ruta_markdown": "docs/decretos/2026/decreto-058-2026.md",
      "ruta_json": "datos/decretos/2026/decreto-058-2026.json",
      "sha256_pdf_original": "222d1c89fd4c0d251fae334cb7da3f04f53641433bf501a4853c379cc57d9ee3",
      "sha256_markdown": "79d54bc30f6e28e3f55d9fc50f7d342ebca10824cc95cd52aac3525bcd1acdfc",
      "estado_revision": "pendiente_revision",
      "estado_publicacion": "normalizado",
      "commit_publicacion": "",
      "notas": "Pendiente de revisión humana. Texto extraído automáticamente desde PDF oficial indicado; verificar contra el PDF antes de publicar como aprobado."
    },
    {
      "tipo_documento": "decreto",
      "numero": "059",
      "anio": "2026",
      "titulo": "Decreto núm. 059-2026",
      "fecha": "30 de Enero 2026 | 18:14",
      "institucion_fuente": "Presidencia de la República Dominicana",
      "url_fuente_oficial": "https://presidencia.gob.do/decretos/59-26",
      "url_pdf_original": "https://presidencia.gob.do//sites/default/files/decree/2026-01/Decreto%2059-26.pdf",
      "fecha_consulta": "2026-07-04",
      "ruta_pdf_local": "archivos/decretos/2026/decreto-059-2026.pdf",
      "ruta_markdown": "docs/decretos/2026/decreto-059-2026.md",
      "ruta_json": "datos/decretos/2026/decreto-059-2026.json",
      "sha256_pdf_original": "5f4e8b2d4d9388d00eb440d6bae6c316cd13c6130834d0b7eda344dcca6eb076",
      "sha256_markdown": "828295609d6622cc2cf3688801a765363a480738269df822ad4ed501ea783d5d",
      "estado_revision": "pendiente_revision",
      "estado_publicacion": "normalizado",
      "commit_publicacion": "",
      "notas": "Pendiente de revisión humana. Texto extraído automáticamente desde PDF oficial indicado; verificar contra el PDF antes de publicar como aprobado."
    },
    {
      "tipo_documento": "decreto",
      "numero": "060",
      "anio": "2026",
      "titulo": "Decreto núm. 060-2026",
      "fecha": "30 de Enero 2026 | 20:03",
      "institucion_fuente": "Presidencia de la República Dominicana",
      "url_fuente_oficial": "https://presidencia.gob.do/decretos/60-26",
      "url_pdf_original": "https://presidencia.gob.do//sites/default/files/decree/2026-01/Decreto%2060-26.pdf",
      "fecha_consulta": "2026-07-04",
      "ruta_pdf_local": "archivos/decretos/2026/decreto-060-2026.pdf",
      "ruta_markdown": "docs/decretos/2026/decreto-060-2026.md",
      "ruta_json": "datos/decretos/2026/decreto-060-2026.json",
      "sha256_pdf_original": "2ea8fb89baac2be7c30425f5b6267f297755bf4154ed08bfdfd6d42cc45bb287",
      "sha256_markdown": "a040077cb5326312362b24f3cab548cb9b494487c2186f4c4a742ba97fcffb25",
      "estado_revision": "pendiente_revision",
      "estado_publicacion": "normalizado",
      "commit_publicacion": "",
      "notas": "Pendiente de revisión humana. Texto extraído automáticamente desde PDF oficial indicado; verificar contra el PDF antes de publicar como aprobado."
    },
    {
      "tipo_documento": "decreto",
      "numero": "065",
      "anio": "2026",
      "titulo": "Decreto núm. 065-2026",
      "fecha": "1 de Febrero 2026 | 19:12",
      "institucion_fuente": "Presidencia de la República Dominicana",
      "url_fuente_oficial": "https://presidencia.gob.do/decretos/65-26",
      "url_pdf_original": "https://presidencia.gob.do//sites/default/files/decree/2026-02/Decreto%2065-26.pdf",
      "fecha_consulta": "2026-07-04",
      "ruta_pdf_local": "archivos/decretos/2026/decreto-065-2026.pdf",
      "ruta_markdown": "docs/decretos/2026/decreto-065-2026.md",
      "ruta_json": "datos/decretos/2026/decreto-065-2026.json",
      "sha256_pdf_original": "5d9baccc8de3c2de0a1baaf6dc82ffe369cbf3ce232aceda805b1bcdd861e180",
      "sha256_markdown": "cefab3c43c16946b4952600cc2dc4aa95f28530040f942b86248c050cd6ac785",
      "estado_revision": "pendiente_revision",
      "estado_publicacion": "normalizado",
      "commit_publicacion": "",
      "notas": "Pendiente de revisión humana. Texto extraído automáticamente desde PDF oficial indicado; verificar contra el PDF antes de publicar como aprobado."
    },
    {
      "tipo_documento": "decreto",
      "numero": "066",
      "anio": "2026",
      "titulo": "Decreto núm. 066-2026",
      "fecha": "1 de Febrero 2026 | 19:18",
      "institucion_fuente": "Presidencia de la República Dominicana",
      "url_fuente_oficial": "https://presidencia.gob.do/decretos/66-26",
      "url_pdf_original": "https://presidencia.gob.do//sites/default/files/decree/2026-02/Decreto%2066-26_2.pdf",
      "fecha_consulta": "2026-07-04",
      "ruta_pdf_local": "archivos/decretos/2026/decreto-066-2026.pdf",
      "ruta_markdown": "docs/decretos/2026/decreto-066-2026.md",
      "ruta_json": "datos/decretos/2026/decreto-066-2026.json",
      "sha256_pdf_original": "bfdcd06e2f6a5905310c496e4c7b5b70013c5266b62dd7c406aafdbb4f564c32",
      "sha256_markdown": "f6055271e2eb70f96c30cc47b5aa8dce103d286580e0b64d1d73dde85fdf71d4",
      "estado_revision": "pendiente_revision",
      "estado_publicacion": "normalizado",
      "commit_publicacion": "",
      "notas": "Pendiente de revisión humana. Texto extraído automáticamente desde PDF oficial indicado; verificar contra el PDF antes de publicar como aprobado."
    },
    {
      "tipo_documento": "decreto",
      "numero": "069",
      "anio": "2026",
      "titulo": "Decreto núm. 069-2026",
      "fecha": "7 de Febrero 2026 | 09:39",
      "institucion_fuente": "Presidencia de la República Dominicana",
      "url_fuente_oficial": "https://presidencia.gob.do/decretos/69-26",
      "url_pdf_original": "https://presidencia.gob.do//sites/default/files/decree/2026-02/Decreto%2069-26.pdf",
      "fecha_consulta": "2026-07-04",
      "ruta_pdf_local": "archivos/decretos/2026/decreto-069-2026.pdf",
      "ruta_markdown": "docs/decretos/2026/decreto-069-2026.md",
      "ruta_json": "datos/decretos/2026/decreto-069-2026.json",
      "sha256_pdf_original": "b8e3c2ac0ae3a2c60caaa7ce9a1676b1618170c5d768e5d81480f1a7fba17fc2",
      "sha256_markdown": "16abcd7626c95edbdbc6abed4227bce539b11bbf8a6d940388b17be617e39338",
      "estado_revision": "pendiente_revision",
      "estado_publicacion": "normalizado",
      "commit_publicacion": "",
      "notas": "Pendiente de revisión humana. Texto extraído automáticamente desde PDF oficial indicado; verificar contra el PDF antes de publicar como aprobado."
    },
    {
      "tipo_documento": "decreto",
      "numero": "070",
      "anio": "2026",
      "titulo": "Decreto núm. 070-2026",
      "fecha": "7 de Febrero 2026 | 09:40",
      "institucion_fuente": "Presidencia de la República Dominicana",
      "url_fuente_oficial": "https://presidencia.gob.do/decretos/70-26",
      "url_pdf_original": "https://presidencia.gob.do//sites/default/files/decree/2026-02/Decreto%2070-26.pdf",
      "fecha_consulta": "2026-07-04",
      "ruta_pdf_local": "archivos/decretos/2026/decreto-070-2026.pdf",
      "ruta_markdown": "docs/decretos/2026/decreto-070-2026.md",
      "ruta_json": "datos/decretos/2026/decreto-070-2026.json",
      "sha256_pdf_original": "4051cb174224c45cf124d5eae0345b38e454e152e55663aa989658237c66df8a",
      "sha256_markdown": "e9011efa9e3c60150ebfb84887087fa3d1de62a983b179a321cff51263c96a29",
      "estado_revision": "pendiente_revision",
      "estado_publicacion": "normalizado",
      "commit_publicacion": "",
      "notas": "Pendiente de revisión humana. Texto extraído automáticamente desde PDF oficial indicado; verificar contra el PDF antes de publicar como aprobado."
    },
    {
      "tipo_documento": "decreto",
      "numero": "071",
      "anio": "2026",
      "titulo": "Decreto núm. 071-2026",
      "fecha": "7 de Febrero 2026 | 09:40",
      "institucion_fuente": "Presidencia de la República Dominicana",
      "url_fuente_oficial": "https://presidencia.gob.do/decretos/71-26",
      "url_pdf_original": "https://presidencia.gob.do//sites/default/files/decree/2026-02/Decreto%2071-26.pdf",
      "fecha_consulta": "2026-07-04",
      "ruta_pdf_local": "archivos/decretos/2026/decreto-071-2026.pdf",
      "ruta_markdown": "docs/decretos/2026/decreto-071-2026.md",
      "ruta_json": "datos/decretos/2026/decreto-071-2026.json",
      "sha256_pdf_original": "1b0dfb4755a56a565ed610e924a2365017ce7a70d7450f8abb6aed91890630ca",
      "sha256_markdown": "fde8abce3161cff2ce91fd3b04b8b69623c3ec64e471618a84c540aed89693b6",
      "estado_revision": "pendiente_revision",
      "estado_publicacion": "normalizado",
      "commit_publicacion": "",
      "notas": "Pendiente de revisión humana. Texto extraído automáticamente desde PDF oficial indicado; verificar contra el PDF antes de publicar como aprobado."
    },
    {
      "tipo_documento": "decreto",
      "numero": "084",
      "anio": "2026",
      "titulo": "Decreto núm. 084-2026",
      "fecha": "9 de Febrero 2026 | 22:12",
      "institucion_fuente": "Presidencia de la República Dominicana",
      "url_fuente_oficial": "https://presidencia.gob.do/decretos/84-26",
      "url_pdf_original": "https://presidencia.gob.do//sites/default/files/decree/2026-02/Decreto%2084-26.pdf",
      "fecha_consulta": "2026-07-04",
      "ruta_pdf_local": "archivos/decretos/2026/decreto-084-2026.pdf",
      "ruta_markdown": "docs/decretos/2026/decreto-084-2026.md",
      "ruta_json": "datos/decretos/2026/decreto-084-2026.json",
      "sha256_pdf_original": "07a05d22286449400182daefb91989bf70e439d40185c377ebcc3920291ee015",
      "sha256_markdown": "ff26252ad2cf111d72e304ea96cb4daaf9c60b5564353fd7777f8fbdcefa37a1",
      "estado_revision": "pendiente_revision",
      "estado_publicacion": "normalizado",
      "commit_publicacion": "",
      "notas": "Pendiente de revisión humana. Texto extraído automáticamente desde PDF oficial indicado; verificar contra el PDF antes de publicar como aprobado."
    },
    {
      "tipo_documento": "decreto",
      "numero": "095",
      "anio": "2026",
      "titulo": "Decreto núm. 095-2026",
      "fecha": "12 de Febrero 2026 | 13:12",
      "institucion_fuente": "Presidencia de la República Dominicana",
      "url_fuente_oficial": "https://presidencia.gob.do/decretos/95-26",
      "url_pdf_original": "https://presidencia.gob.do//sites/default/files/decree/2026-02/Decreto%2095-26.pdf",
      "fecha_consulta": "2026-07-04",
      "ruta_pdf_local": "archivos/decretos/2026/decreto-095-2026.pdf",
      "ruta_markdown": "docs/decretos/2026/decreto-095-2026.md",
      "ruta_json": "datos/decretos/2026/decreto-095-2026.json",
      "sha256_pdf_original": "fe7c54f8cf8dc64decf17d469f4b67e027f307b5333edbbe312b5d436c211110",
      "sha256_markdown": "42fffd86d20c27a07b6fe931bf5d0c2de25852a6a9cc6ad213ba4c9803823e34",
      "estado_revision": "pendiente_revision",
      "estado_publicacion": "normalizado",
      "commit_publicacion": "",
      "notas": "Pendiente de revisión humana. Texto extraído automáticamente desde PDF oficial indicado; verificar contra el PDF antes de publicar como aprobado."
    },
    {
      "tipo_documento": "decreto",
      "numero": "111",
      "anio": "2026",
      "titulo": "Decreto núm. 111-2026",
      "fecha": "17 de Febrero 2026 | 18:27",
      "institucion_fuente": "Presidencia de la República Dominicana",
      "url_fuente_oficial": "https://presidencia.gob.do/decretos/111-26",
      "url_pdf_original": "https://presidencia.gob.do//sites/default/files/decree/2026-02/Decreto%20111-26.pdf",
      "fecha_consulta": "2026-07-04",
      "ruta_pdf_local": "archivos/decretos/2026/decreto-111-2026.pdf",
      "ruta_markdown": "docs/decretos/2026/decreto-111-2026.md",
      "ruta_json": "datos/decretos/2026/decreto-111-2026.json",
      "sha256_pdf_original": "7c0bbf5907f14e31cd1e21563610bb4786021cb086736f924b0cf504cca19276",
      "sha256_markdown": "7a08bf4d048f9d5f01a06f749d6152c7f5eab59c12e552151e983a12fadc5fee",
      "estado_revision": "pendiente_revision",
      "estado_publicacion": "normalizado",
      "commit_publicacion": "",
      "notas": "Pendiente de revisión humana. Texto extraído automáticamente desde PDF oficial indicado; verificar contra el PDF antes de publicar como aprobado."
    },
    {
      "tipo_documento": "decreto",
      "numero": "133",
      "anio": "2026",
      "titulo": "Decreto núm. 133-2026",
      "fecha": "27 de Febrero 2026 | 22:25",
      "institucion_fuente": "Presidencia de la República Dominicana",
      "url_fuente_oficial": "https://presidencia.gob.do/decretos/133-26",
      "url_pdf_original": "https://presidencia.gob.do//sites/default/files/decree/2026-02/Decreto%20133-26.pdf",
      "fecha_consulta": "2026-07-04",
      "ruta_pdf_local": "archivos/decretos/2026/decreto-133-2026.pdf",
      "ruta_markdown": "docs/decretos/2026/decreto-133-2026.md",
      "ruta_json": "datos/decretos/2026/decreto-133-2026.json",
      "sha256_pdf_original": "795c1c11e96053cd0a43c3adddce3a058a46a4c3211a827faf849b2d5e96e520",
      "sha256_markdown": "3d2c3b57f1e59e03bb0a671830d11aab304916f57a501aa2d0ecd227c96bf6b3",
      "estado_revision": "pendiente_revision",
      "estado_publicacion": "normalizado",
      "commit_publicacion": "",
      "notas": "Pendiente de revisión humana. Texto extraído automáticamente desde PDF oficial indicado; verificar contra el PDF antes de publicar como aprobado."
    },
    {
      "tipo_documento": "decreto",
      "numero": "134",
      "anio": "2026",
      "titulo": "Decreto núm. 134-2026",
      "fecha": "27 de Febrero 2026 | 22:16",
      "institucion_fuente": "Presidencia de la República Dominicana",
      "url_fuente_oficial": "https://presidencia.gob.do/decretos/134-26",
      "url_pdf_original": "https://presidencia.gob.do//sites/default/files/decree/2026-02/Decreto%20134-24.pdf",
      "fecha_consulta": "2026-07-04",
      "ruta_pdf_local": "archivos/decretos/2026/decreto-134-2026.pdf",
      "ruta_markdown": "docs/decretos/2026/decreto-134-2026.md",
      "ruta_json": "datos/decretos/2026/decreto-134-2026.json",
      "sha256_pdf_original": "dc5350b90232f59da51287b3c9a763bc3be7b302aa36f68def1f8f9cd10ea18f",
      "sha256_markdown": "54bd4b5aa5a095358ac1751b83722e1a81a81d7887c1a9d7b2deb9cbd425d636",
      "estado_revision": "pendiente_revision",
      "estado_publicacion": "normalizado",
      "commit_publicacion": "",
      "notas": "Pendiente de revisión humana. Texto extraído automáticamente desde PDF oficial indicado; verificar contra el PDF antes de publicar como aprobado."
    },
    {
      "tipo_documento": "decreto",
      "numero": "135",
      "anio": "2026",
      "titulo": "Decreto núm. 135-2026",
      "fecha": "28 de Febrero 2026 | 08:23",
      "institucion_fuente": "Presidencia de la República Dominicana",
      "url_fuente_oficial": "https://presidencia.gob.do/decretos/135-26",
      "url_pdf_original": "https://presidencia.gob.do//sites/default/files/decree/2026-02/Decreto%20135-26.pdf",
      "fecha_consulta": "2026-07-04",
      "ruta_pdf_local": "archivos/decretos/2026/decreto-135-2026.pdf",
      "ruta_markdown": "docs/decretos/2026/decreto-135-2026.md",
      "ruta_json": "datos/decretos/2026/decreto-135-2026.json",
      "sha256_pdf_original": "867a7f092b0c151e6be959af8b02177c912b1f69de6095fe2f70f05d50221b05",
      "sha256_markdown": "7b96c496f24e4195612aa6c83552e97d92652c32d72d0e52ad0c59649a9dad29",
      "estado_revision": "pendiente_revision",
      "estado_publicacion": "normalizado",
      "commit_publicacion": "",
      "notas": "Pendiente de revisión humana. Texto extraído automáticamente desde PDF oficial indicado; verificar contra el PDF antes de publicar como aprobado."
    },
    {
      "tipo_documento": "decreto",
      "numero": "197",
      "anio": "2026",
      "titulo": "Decreto núm. 197-2026",
      "fecha": "15 de Abril 2026 | 15:23",
      "institucion_fuente": "Presidencia de la República Dominicana",
      "url_fuente_oficial": "https://presidencia.gob.do/decretos/197-26",
      "url_pdf_original": "https://presidencia.gob.do//sites/default/files/decree/2026-04/Decreto%20197-26.pdf",
      "fecha_consulta": "2026-07-04",
      "ruta_pdf_local": "archivos/decretos/2026/decreto-197-2026.pdf",
      "ruta_markdown": "docs/decretos/2026/decreto-197-2026.md",
      "ruta_json": "datos/decretos/2026/decreto-197-2026.json",
      "sha256_pdf_original": "1f5c1d8d1965687feb0373bffcfe5d3ea495ce9a4a5371f9d4d2620d9944bdf6",
      "sha256_markdown": "f76954ce64e1edce1f1157f9cc3c313dd43650e98f6ac54422bba05cc342fd19",
      "estado_revision": "pendiente_revision",
      "estado_publicacion": "normalizado",
      "commit_publicacion": "",
      "notas": "Pendiente de revisión humana. Texto extraído automáticamente desde PDF oficial indicado; verificar contra el PDF antes de publicar como aprobado."
    },
    {
      "tipo_documento": "decreto",
      "numero": "200",
      "anio": "2026",
      "titulo": "Decreto núm. 200-2026",
      "fecha": "26 de Marzo 2026 | 19:24",
      "institucion_fuente": "Presidencia de la República Dominicana",
      "url_fuente_oficial": "https://presidencia.gob.do/decretos/200-26",
      "url_pdf_original": "https://presidencia.gob.do//sites/default/files/decree/2026-03/Decreto%20200-26.pdf",
      "fecha_consulta": "2026-07-04",
      "ruta_pdf_local": "archivos/decretos/2026/decreto-200-2026.pdf",
      "ruta_markdown": "docs/decretos/2026/decreto-200-2026.md",
      "ruta_json": "datos/decretos/2026/decreto-200-2026.json",
      "sha256_pdf_original": "7790a5c0095ab0365707d8aa0a75c34f677288d5fac37344ac6504efb82fc7a4",
      "sha256_markdown": "d38291d44aaa61ef41b2ec9e794610770180bf21139e2cffd4153dc7d20b7e08",
      "estado_revision": "pendiente_revision",
      "estado_publicacion": "normalizado",
      "commit_publicacion": "",
      "notas": "Pendiente de revisión humana. Texto extraído automáticamente desde PDF oficial indicado; verificar contra el PDF antes de publicar como aprobado."
    },
    {
      "tipo_documento": "decreto",
      "numero": "234",
      "anio": "2026",
      "titulo": "Decreto núm. 234-2026",
      "fecha": "13 de Abril 2026 | 07:14",
      "institucion_fuente": "Presidencia de la República Dominicana",
      "url_fuente_oficial": "https://presidencia.gob.do/decretos/234-26",
      "url_pdf_original": "https://presidencia.gob.do//sites/default/files/decree/2026-04/Decreto%20234-26.pdf",
      "fecha_consulta": "2026-07-04",
      "ruta_pdf_local": "archivos/decretos/2026/decreto-234-2026.pdf",
      "ruta_markdown": "docs/decretos/2026/decreto-234-2026.md",
      "ruta_json": "datos/decretos/2026/decreto-234-2026.json",
      "sha256_pdf_original": "77be59f073b92556e2b17a4c5b623ae176c0fa094f707aa8c119d2ce7c42697b",
      "sha256_markdown": "af8b9ed0c34e7066ed21c3981766fe5fda2a28f7f5ddb3ca6986b84aa8454d7f",
      "estado_revision": "pendiente_revision",
      "estado_publicacion": "normalizado",
      "commit_publicacion": "",
      "notas": "Pendiente de revisión humana. Texto extraído automáticamente desde PDF oficial indicado; verificar contra el PDF antes de publicar como aprobado."
    },
    {
      "tipo_documento": "decreto",
      "numero": "236",
      "anio": "2026",
      "titulo": "Decreto núm. 236-2026",
      "fecha": "27 de Abril 2026 | 20:48",
      "institucion_fuente": "Presidencia de la República Dominicana",
      "url_fuente_oficial": "https://presidencia.gob.do/decretos/236-26",
      "url_pdf_original": "https://presidencia.gob.do//sites/default/files/decree/2026-04/Decreto%20236-26.pdf",
      "fecha_consulta": "2026-07-04",
      "ruta_pdf_local": "archivos/decretos/2026/decreto-236-2026.pdf",
      "ruta_markdown": "docs/decretos/2026/decreto-236-2026.md",
      "ruta_json": "datos/decretos/2026/decreto-236-2026.json",
      "sha256_pdf_original": "3fbff786cdb6f0cf2197b8eb72105c9672edb44b3cec24996ca575504dd2f9e6",
      "sha256_markdown": "10765a16f29e31f81f7093fbeb14f50321a2cbf1dfd0dfb8160045b0793c7f37",
      "estado_revision": "pendiente_revision",
      "estado_publicacion": "normalizado",
      "commit_publicacion": "",
      "notas": "Pendiente de revisión humana. Texto extraído automáticamente desde PDF oficial indicado; verificar contra el PDF antes de publicar como aprobado."
    },
    {
      "tipo_documento": "decreto",
      "numero": "240",
      "anio": "2026",
      "titulo": "Decreto núm. 240-2026",
      "fecha": "14 de Abril 2026 | 18:15",
      "institucion_fuente": "Presidencia de la República Dominicana",
      "url_fuente_oficial": "https://presidencia.gob.do/decretos/240-26",
      "url_pdf_original": "https://presidencia.gob.do//sites/default/files/decree/2026-04/Decreto%20240-26.pdf",
      "fecha_consulta": "2026-07-04",
      "ruta_pdf_local": "archivos/decretos/2026/decreto-240-2026.pdf",
      "ruta_markdown": "docs/decretos/2026/decreto-240-2026.md",
      "ruta_json": "datos/decretos/2026/decreto-240-2026.json",
      "sha256_pdf_original": "2d47b3e5691ce6396a2d3562a9afed200d6e99eebe9e791eb451514ceb9061d8",
      "sha256_markdown": "6e5d4b9d276e174af58710f47845bb7d64672b2eccc47eadf10ec757e8865255",
      "estado_revision": "pendiente_revision",
      "estado_publicacion": "normalizado",
      "commit_publicacion": "",
      "notas": "Pendiente de revisión humana. Texto extraído automáticamente desde PDF oficial indicado; verificar contra el PDF antes de publicar como aprobado."
    },
    {
      "tipo_documento": "decreto",
      "numero": "241",
      "anio": "2026",
      "titulo": "Decreto núm. 241-2026",
      "fecha": "14 de Abril 2026 | 18:18",
      "institucion_fuente": "Presidencia de la República Dominicana",
      "url_fuente_oficial": "https://presidencia.gob.do/decretos/241-26",
      "url_pdf_original": "https://presidencia.gob.do//sites/default/files/decree/2026-04/Decreto%20241-26.pdf",
      "fecha_consulta": "2026-07-04",
      "ruta_pdf_local": "archivos/decretos/2026/decreto-241-2026.pdf",
      "ruta_markdown": "docs/decretos/2026/decreto-241-2026.md",
      "ruta_json": "datos/decretos/2026/decreto-241-2026.json",
      "sha256_pdf_original": "0c7cfbd53993fdae283373617b88cc89e7c15c3d9e9128cd679562a0813bf2b1",
      "sha256_markdown": "85d40075e24ecab700a635be8bca1fe3c0b37a3cc4d6a2f0adc3cc96ec3d010d",
      "estado_revision": "pendiente_revision",
      "estado_publicacion": "normalizado",
      "commit_publicacion": "",
      "notas": "Pendiente de revisión humana. Texto extraído automáticamente desde PDF oficial indicado; verificar contra el PDF antes de publicar como aprobado."
    },
    {
      "tipo_documento": "decreto",
      "numero": "242",
      "anio": "2026",
      "titulo": "Decreto núm. 242-2026",
      "fecha": "14 de Abril 2026 | 18:29",
      "institucion_fuente": "Presidencia de la República Dominicana",
      "url_fuente_oficial": "https://presidencia.gob.do/decretos/242-26",
      "url_pdf_original": "https://presidencia.gob.do//sites/default/files/decree/2026-04/Decreto%20242-26.pdf",
      "fecha_consulta": "2026-07-04",
      "ruta_pdf_local": "archivos/decretos/2026/decreto-242-2026.pdf",
      "ruta_markdown": "docs/decretos/2026/decreto-242-2026.md",
      "ruta_json": "datos/decretos/2026/decreto-242-2026.json",
      "sha256_pdf_original": "c88aba705db86e7bd68027735973f8adb67d46e36ee737035f7302134d4d7f8b",
      "sha256_markdown": "c754e24cc1af81116d124ce5977f079d2f3d0d63dd4ff1c43d7c6b7a6a09ca35",
      "estado_revision": "pendiente_revision",
      "estado_publicacion": "normalizado",
      "commit_publicacion": "",
      "notas": "Pendiente de revisión humana. Texto extraído automáticamente desde PDF oficial indicado; verificar contra el PDF antes de publicar como aprobado."
    },
    {
      "tipo_documento": "decreto",
      "numero": "243",
      "anio": "2026",
      "titulo": "Decreto núm. 243-2026",
      "fecha": "14 de Abril 2026 | 18:31",
      "institucion_fuente": "Presidencia de la República Dominicana",
      "url_fuente_oficial": "https://presidencia.gob.do/decretos/243-26",
      "url_pdf_original": "https://presidencia.gob.do//sites/default/files/decree/2026-04/Decreto%20243-26.pdf",
      "fecha_consulta": "2026-07-04",
      "ruta_pdf_local": "archivos/decretos/2026/decreto-243-2026.pdf",
      "ruta_markdown": "docs/decretos/2026/decreto-243-2026.md",
      "ruta_json": "datos/decretos/2026/decreto-243-2026.json",
      "sha256_pdf_original": "928b0a09736bc7022c0e4d3e68de707e89d47a15f5205357ed5f691d71f98d80",
      "sha256_markdown": "6eccf42fec36454a279435616b21bcc341c2b7333e2ba1382a5664d688b6391c",
      "estado_revision": "pendiente_revision",
      "estado_publicacion": "normalizado",
      "commit_publicacion": "",
      "notas": "Pendiente de revisión humana. Texto extraído automáticamente desde PDF oficial indicado; verificar contra el PDF antes de publicar como aprobado."
    },
    {
      "tipo_documento": "decreto",
      "numero": "245",
      "anio": "2026",
      "titulo": "Decreto núm. 245-2026",
      "fecha": "16 de Abril 2026 | 12:54",
      "institucion_fuente": "Presidencia de la República Dominicana",
      "url_fuente_oficial": "https://presidencia.gob.do/decretos/245-26",
      "url_pdf_original": "https://presidencia.gob.do//sites/default/files/decree/2026-04/Decreto%20245-26.pdf",
      "fecha_consulta": "2026-07-04",
      "ruta_pdf_local": "archivos/decretos/2026/decreto-245-2026.pdf",
      "ruta_markdown": "docs/decretos/2026/decreto-245-2026.md",
      "ruta_json": "datos/decretos/2026/decreto-245-2026.json",
      "sha256_pdf_original": "cdd2b7c0880db0daed01d99ba413b12e9dce55e5647bd494337877ae9f06411d",
      "sha256_markdown": "1f7d072f050eb2ccb5c6a044ff2582a28ac42fc476aa70f1ec2fd80da8e37665",
      "estado_revision": "pendiente_revision",
      "estado_publicacion": "normalizado",
      "commit_publicacion": "",
      "notas": "Pendiente de revisión humana. Texto extraído automáticamente desde PDF oficial indicado; verificar contra el PDF antes de publicar como aprobado."
    },
    {
      "tipo_documento": "decreto",
      "numero": "285",
      "anio": "2026",
      "titulo": "Decreto núm. 285-2026",
      "fecha": "27 de Abril 2026 | 20:54",
      "institucion_fuente": "Presidencia de la República Dominicana",
      "url_fuente_oficial": "https://presidencia.gob.do/decretos/285-26",
      "url_pdf_original": "https://presidencia.gob.do//sites/default/files/decree/2026-04/Decreto%20285-26.pdf",
      "fecha_consulta": "2026-07-04",
      "ruta_pdf_local": "archivos/decretos/2026/decreto-285-2026.pdf",
      "ruta_markdown": "docs/decretos/2026/decreto-285-2026.md",
      "ruta_json": "datos/decretos/2026/decreto-285-2026.json",
      "sha256_pdf_original": "418e24b7d852bf5ca41958b97883ed31b6f5b329f5d8ba6f7c4b9e2c2ad9e93b",
      "sha256_markdown": "502cda76d4a8f284be6540f48976de5d68e72fee41d72020e3ef2e16fd858411",
      "estado_revision": "pendiente_revision",
      "estado_publicacion": "normalizado",
      "commit_publicacion": "",
      "notas": "Pendiente de revisión humana. Texto extraído automáticamente desde PDF oficial indicado; verificar contra el PDF antes de publicar como aprobado."
    },
    {
      "tipo_documento": "decreto",
      "numero": "298",
      "anio": "2026",
      "titulo": "Decreto núm. 298-2026",
      "fecha": "2 de Mayo 2026 | 12:42",
      "institucion_fuente": "Presidencia de la República Dominicana",
      "url_fuente_oficial": "https://presidencia.gob.do/decretos/298-26",
      "url_pdf_original": "https://presidencia.gob.do//sites/default/files/decree/2026-05/Decreto%20298-26.pdf",
      "fecha_consulta": "2026-07-04",
      "ruta_pdf_local": "archivos/decretos/2026/decreto-298-2026.pdf",
      "ruta_markdown": "docs/decretos/2026/decreto-298-2026.md",
      "ruta_json": "datos/decretos/2026/decreto-298-2026.json",
      "sha256_pdf_original": "4db9ec8127d4305cb02f6663aaa7b905fe5315cdb79796d3dd7312585ba89b0d",
      "sha256_markdown": "26e7ee3657d208eab24282113c10099fec6c566d253cc17a0d2c2d826d9d78ad",
      "estado_revision": "pendiente_revision",
      "estado_publicacion": "normalizado",
      "commit_publicacion": "",
      "notas": "Pendiente de revisión humana. Texto extraído automáticamente desde PDF oficial indicado; verificar contra el PDF antes de publicar como aprobado."
    },
    {
      "tipo_documento": "decreto",
      "numero": "309",
      "anio": "2026",
      "titulo": "Decreto núm. 309-2026",
      "fecha": "7 de Mayo 2026 | 13:22",
      "institucion_fuente": "Presidencia de la República Dominicana",
      "url_fuente_oficial": "https://presidencia.gob.do/decretos/309-26",
      "url_pdf_original": "https://presidencia.gob.do//sites/default/files/decree/2026-05/Decreto%20309-26.pdf",
      "fecha_consulta": "2026-07-04",
      "ruta_pdf_local": "archivos/decretos/2026/decreto-309-2026.pdf",
      "ruta_markdown": "docs/decretos/2026/decreto-309-2026.md",
      "ruta_json": "datos/decretos/2026/decreto-309-2026.json",
      "sha256_pdf_original": "6be6b5a310ec59d08ce9ace2cd3212e2ca53d47612ee2a3c954e521918a7cfec",
      "sha256_markdown": "44c47244593a2318de529ca62015d0f2a9073e8faf402262cc9be0023262cda9",
      "estado_revision": "pendiente_revision",
      "estado_publicacion": "normalizado",
      "commit_publicacion": "",
      "notas": "Pendiente de revisión humana. Texto extraído automáticamente desde PDF oficial indicado; verificar contra el PDF antes de publicar como aprobado."
    },
    {
      "tipo_documento": "decreto",
      "numero": "311",
      "anio": "2026",
      "titulo": "Decreto núm. 311-2026",
      "fecha": "7 de Mayo 2026 | 13:37",
      "institucion_fuente": "Presidencia de la República Dominicana",
      "url_fuente_oficial": "https://presidencia.gob.do/decretos/311-26",
      "url_pdf_original": "https://presidencia.gob.do//sites/default/files/decree/2026-05/Decreto%20311-26.pdf",
      "fecha_consulta": "2026-07-04",
      "ruta_pdf_local": "archivos/decretos/2026/decreto-311-2026.pdf",
      "ruta_markdown": "docs/decretos/2026/decreto-311-2026.md",
      "ruta_json": "datos/decretos/2026/decreto-311-2026.json",
      "sha256_pdf_original": "c4f703b2504d735691a79be8c046d64726bbc379c556fe6e694724b450145993",
      "sha256_markdown": "2a10ec4b36af3da4ed04c40ea190ae6ce5f6fbcaac5ffb3d39f7bcaee331fe69",
      "estado_revision": "pendiente_revision",
      "estado_publicacion": "normalizado",
      "commit_publicacion": "",
      "notas": "Pendiente de revisión humana. Texto extraído automáticamente desde PDF oficial indicado; verificar contra el PDF antes de publicar como aprobado."
    },
    {
      "tipo_documento": "decreto",
      "numero": "312",
      "anio": "2026",
      "titulo": "Decreto núm. 312-2026",
      "fecha": "7 de Mayo 2026 | 13:38",
      "institucion_fuente": "Presidencia de la República Dominicana",
      "url_fuente_oficial": "https://presidencia.gob.do/decretos/312-26",
      "url_pdf_original": "https://presidencia.gob.do//sites/default/files/decree/2026-05/Decreto%20312-26.pdf",
      "fecha_consulta": "2026-07-04",
      "ruta_pdf_local": "archivos/decretos/2026/decreto-312-2026.pdf",
      "ruta_markdown": "docs/decretos/2026/decreto-312-2026.md",
      "ruta_json": "datos/decretos/2026/decreto-312-2026.json",
      "sha256_pdf_original": "2a4d121d1503fad150ffbed9fc294c3ba94e8b09d162374ddaed7b8809fc2e07",
      "sha256_markdown": "311393cfeaffef3f56c539dd40aa281d89690a032a11eb34a98ff5f95b93c10d",
      "estado_revision": "pendiente_revision",
      "estado_publicacion": "normalizado",
      "commit_publicacion": "",
      "notas": "Pendiente de revisión humana. Texto extraído automáticamente desde PDF oficial indicado; verificar contra el PDF antes de publicar como aprobado."
    },
    {
      "tipo_documento": "decreto",
      "numero": "330",
      "anio": "2026",
      "titulo": "Decreto núm. 330-2026",
      "fecha": "15 de Mayo 2026 | 19:41",
      "institucion_fuente": "Presidencia de la República Dominicana",
      "url_fuente_oficial": "https://presidencia.gob.do/decretos/330-26",
      "url_pdf_original": "https://presidencia.gob.do//sites/default/files/decree/2026-05/Decreto%20330-26.pdf",
      "fecha_consulta": "2026-07-04",
      "ruta_pdf_local": "archivos/decretos/2026/decreto-330-2026.pdf",
      "ruta_markdown": "docs/decretos/2026/decreto-330-2026.md",
      "ruta_json": "datos/decretos/2026/decreto-330-2026.json",
      "sha256_pdf_original": "7a2c49c0861b24448f5e836bba950cfe238975a1b4e2cb3847576f0061aa04dc",
      "sha256_markdown": "c703e96a0179a62ec7790d0a86ab85a92b1092f0621e44a0b87e9c1ec78f5fa7",
      "estado_revision": "pendiente_revision",
      "estado_publicacion": "normalizado",
      "commit_publicacion": "",
      "notas": "Pendiente de revisión humana. Texto extraído automáticamente desde PDF oficial indicado; verificar contra el PDF antes de publicar como aprobado."
    },
    {
      "tipo_documento": "decreto",
      "numero": "352",
      "anio": "2026",
      "titulo": "Decreto núm. 352-2026",
      "fecha": "2 de Junio 2026 | 19:41",
      "institucion_fuente": "Presidencia de la República Dominicana",
      "url_fuente_oficial": "https://presidencia.gob.do/decretos/352-26",
      "url_pdf_original": "https://presidencia.gob.do//sites/default/files/decree/2026-06/Decreto%20352-26.pdf",
      "fecha_consulta": "2026-07-04",
      "ruta_pdf_local": "archivos/decretos/2026/decreto-352-2026.pdf",
      "ruta_markdown": "docs/decretos/2026/decreto-352-2026.md",
      "ruta_json": "datos/decretos/2026/decreto-352-2026.json",
      "sha256_pdf_original": "73c5bff988188c2cb63fa0c4bcc0d7b5fd2c374e4ec140465d057ab5d58fb504",
      "sha256_markdown": "142b261c6b798ea44672fb45cc2f7e2e277ee0d78c81452c780b6828ae070f9d",
      "estado_revision": "pendiente_revision",
      "estado_publicacion": "normalizado",
      "commit_publicacion": "",
      "notas": "Pendiente de revisión humana. Texto extraído automáticamente desde PDF oficial indicado; verificar contra el PDF antes de publicar como aprobado."
    },
    {
      "tipo_documento": "decreto",
      "numero": "409",
      "anio": "2026",
      "titulo": "Decreto núm. 409-2026",
      "fecha": "20 de Junio 2026 | 10:24",
      "institucion_fuente": "Presidencia de la República Dominicana",
      "url_fuente_oficial": "https://presidencia.gob.do/decretos/409-26",
      "url_pdf_original": "https://presidencia.gob.do//sites/default/files/decree/2026-06/Decreto%20409-26.pdf",
      "fecha_consulta": "2026-07-04",
      "ruta_pdf_local": "archivos/decretos/2026/decreto-409-2026.pdf",
      "ruta_markdown": "docs/decretos/2026/decreto-409-2026.md",
      "ruta_json": "datos/decretos/2026/decreto-409-2026.json",
      "sha256_pdf_original": "a1f801ddeb53d41f6bf0db24e2d177282fe06a5e550680bb992181d930eadc8c",
      "sha256_markdown": "197efc2bdd41cc7e42856efef96a8249a0e47faa8284778fd322245a172f274f",
      "estado_revision": "pendiente_revision",
      "estado_publicacion": "normalizado",
      "commit_publicacion": "",
      "notas": "Pendiente de revisión humana. Texto extraído automáticamente desde PDF oficial indicado; verificar contra el PDF antes de publicar como aprobado."
    },
    {
      "tipo_documento": "decreto",
      "numero": "438",
      "anio": "2026",
      "titulo": "Decreto núm. 438-2026",
      "fecha": "1 de Julio 2026 | 09:05",
      "institucion_fuente": "Presidencia de la República Dominicana",
      "url_fuente_oficial": "https://presidencia.gob.do/decretos/438-26",
      "url_pdf_original": "https://presidencia.gob.do//sites/default/files/decree/2026-07/Decreto%20438-26.pdf",
      "fecha_consulta": "2026-07-04",
      "ruta_pdf_local": "archivos/decretos/2026/decreto-438-2026.pdf",
      "ruta_markdown": "docs/decretos/2026/decreto-438-2026.md",
      "ruta_json": "datos/decretos/2026/decreto-438-2026.json",
      "sha256_pdf_original": "d63c1e456bfbb4ad1b198e69e71ea1383be3213c2c54ee5d8a4f269d4c186623",
      "sha256_markdown": "ce8b17459d403ed5185cfe36f20e06b16d6fce1285513d544217d3c4294b8eaa",
      "estado_revision": "pendiente_revision",
      "estado_publicacion": "normalizado",
      "commit_publicacion": "",
      "notas": "Pendiente de revisión humana. Texto extraído automáticamente desde PDF oficial indicado; verificar contra el PDF antes de publicar como aprobado."
    },
    {
      "tipo_documento": "decreto",
      "numero": "444",
      "anio": "2026",
      "titulo": "Decreto núm. 444-2026",
      "fecha": "1 de Julio 2026 | 12:20",
      "institucion_fuente": "Presidencia de la República Dominicana",
      "url_fuente_oficial": "https://presidencia.gob.do/decretos/444-26",
      "url_pdf_original": "https://presidencia.gob.do//sites/default/files/decree/2026-07/Decreto%20444-26.pdf",
      "fecha_consulta": "2026-07-04",
      "ruta_pdf_local": "archivos/decretos/2026/decreto-444-2026.pdf",
      "ruta_markdown": "docs/decretos/2026/decreto-444-2026.md",
      "ruta_json": "datos/decretos/2026/decreto-444-2026.json",
      "sha256_pdf_original": "eb138490a009ff03574e6c9c8f4999570116bf8f64b5989d52a9bf16eb737302",
      "sha256_markdown": "bb20e41364f5a20eab8779da1b3cb32e29e616a51b22b49445b24aa02436739b",
      "estado_revision": "pendiente_revision",
      "estado_publicacion": "normalizado",
      "commit_publicacion": "",
      "notas": "Pendiente de revisión humana. Texto extraído automáticamente desde PDF oficial indicado; verificar contra el PDF antes de publicar como aprobado."
    }
  ]
}
